{
  "currentDay": 3,
  "publishedDays": [
    1,
    2
  ],
  "startedAt": "2026-06-26T04:54:11.403Z",
  "pieza": "Hera",
  "material": "Cráneo de toro real con joyería y turquesa aplicadas a mano",
  "tamaño": "65 cm alto x 70 cm ancho (punta a punta de cuernos)",
  "ubicacion": "Estudio de Arte ARCT (visitas privadas con cita)",
  "precio": "Consultar vía WhatsApp",
  "whatsapp": "+52 444 510 1553",
  "respuestaOficial": "marketing/respuestas-comerciales.md > Opción 1",
  "estado": "EN VENTA — Publicando diariamente hasta que se venda"
}